peanut_sh/__init__.py
peanut_sh/app.py
peanut_sh/daemon.py
peanut_sh-0.0.4.dist-info/METADATA
peanut_sh-0.0.4.dist-info/WHEEL
peanut_sh-0.0.4.dist-info/entry_points.txt
peanut_sh-0.0.4.dist-info/top_level.txt
peanut_sh-0.0.4.dist-info/RECORD
